Metadata-Version: 2.1
Name: pyquine
Version: 0.1
Summary: The best `import quine`
Home-page: https://github.com/gramkraxor/pyquine
Author: Gramkraxor
Author-email: gram@krax.dev
License: Unlicense
Keywords: quine
Platform: UNKNOWN
Classifier: License :: Public Domain
Classifier: Natural Language :: English
Classifier: Operating System :: OS Independent
Classifier: Programming Language :: Python :: 3
Requires-Python: >=3
